climatiq_mcp_server/__init__.py
climatiq_mcp_server/server.py
climatiq_mcp_server/tools.py
iflow_mcp_climatiq_mcp_server-0.2.0.dist-info/METADATA
iflow_mcp_climatiq_mcp_server-0.2.0.dist-info/WHEEL
iflow_mcp_climatiq_mcp_server-0.2.0.dist-info/entry_points.txt
iflow_mcp_climatiq_mcp_server-0.2.0.dist-info/licenses/LICENSE
iflow_mcp_climatiq_mcp_server-0.2.0.dist-info/RECORD
