Metadata-Version: 2.4
Name: iflow-mcp_climatiq-mcp-server
Version: 0.2.0
Summary: Climatiq MCP server for carbon emission calculations
Project-URL: Homepage, https://github.com/yourusername/climatiq-mcp-server
Project-URL: Documentation, https://github.com/yourusername/climatiq-mcp-server#readme
Author-email: Jagan Shanmugam <jaganshanmugam@outlook.com>
License-File: LICENSE
Requires-Python: >=3.11.9
Requires-Dist: httpx>=0.25.2
Requires-Dist: mcp[cli]>=1.4.1
Requires-Dist: pydantic>=2.10.6
Requires-Dist: python-dotenv>=1.0.0
Requires-Dist: rich>=13.5.0
